vault/.version
vault/__classpath__.py
vault/__init__.py
vault/__main__.py
vault/welcome.txt
vault/core/__init__.py
vault/core/vault.py
vault/core/vault_config.py
vault/core/vault_repository.py
vault/core/vault_service.py
vault/domain/__init__.py
vault/domain/vault_entry.py
vault/exception/__init__.py
vault/exception/exceptions.py
vault/resources/application.properties
vault/resources/sample.vault
hspylib_vault-0.9.137.dist-info/METADATA
hspylib_vault-0.9.137.dist-info/WHEEL
hspylib_vault-0.9.137.dist-info/top_level.txt
hspylib_vault-0.9.137.dist-info/RECORD
